{
  "channels": [
    {
      "channelId": "-1002433563412",
      "title": "teste",
      "memberCount": 2,
      "category": "100-1000",
      "ownerId": "7889275343",
      "inviteLink": "https://t.me/+x_P70bm5gr9mZjcx",
      "isApproved": false,
      "type": "channel"
    },
    {
      "channelId": "-1002416410926",
      "title": "test",
      "memberCount": 2,
      "category": "100-1000",
      "ownerId": "7889275343",
      "inviteLink": "https://t.me/+RSeQjWrXB6tiZWY5",
      "isApproved": false,
      "type": "supergroup"
    },
    {
      "channelId": "-1002360690208",
      "title": "Videos Completos",
      "memberCount": 22,
      "category": "100-1000",
      "ownerId": "7889275343",
      "inviteLink": "https://t.me/+EM26mnPWqcM4OGJh",
      "isApproved": false,
      "type": "supergroup"
    }
  ],
  "users": [
    {
      "userId": "7889275343",
      "channelCount": 3,
      "isBanned": false
    }
  ]
}